ansitoolkit/__init__.py
ansitoolkit/colors.py
ansitoolkit/core/__init__.py
ansitoolkit/core/constants.py
ansitoolkit/core/generator.py
ansitoolkit/cursorMovement.py
ansitoolkit/cursorShape.py
ansitoolkit/deviceStatus.py
ansitoolkit/effects.py
ansitoolkit/graphicsAndCharacterSets.py
ansitoolkit/keyboardAndInputModes.py
ansitoolkit/screenControl.py
ansitoolkit/scrollingRegion.py
ansitoolkit-0.1.15.dist-info/LICENSE
ansitoolkit-0.1.15.dist-info/METADATA
ansitoolkit-0.1.15.dist-info/WHEEL
ansitoolkit-0.1.15.dist-info/RECORD
