Metadata-Version: 2.3
Name: ansitoolkit
Version: 0.1.15
Summary: ansitoolkit makes terminal magic easy — your go-to toolkit for hassle-free ANSI escape codes and colorful, dynamic terminal output!
Keywords: ansi,cli
Author: hyperoot
Author-email: hyperoot.tech@proton.me
Requires-Python: >=3.12,<4.0
Classifier: Programming Language :: Python :: 3
Classifier: Programming Language :: Python :: 3.12
Classifier: Programming Language :: Python :: 3.13
Requires-Dist: cairosvg (>=2.7.1,<3.0.0)
Requires-Dist: pillow (>=11.1.0,<12.0.0)
Project-URL: Documentation, https://ansitoolkit.hyperoot.dev/
Project-URL: Homepage, https://ansitoolkit.hyperoot.dev/
Project-URL: Repository, https://github.com/HYP3R00T/AnsiToolkit
